freighter/__init__.py
freighter/alamos.py
freighter/codec.py
freighter/context.py
freighter/exceptions.py
freighter/http.py
freighter/mock.py
freighter/py.typed
freighter/stream.py
freighter/transport.py
freighter/unary.py
freighter/url.py
freighter/websocket.py
synnax_freighter-0.49.0.dist-info/METADATA
synnax_freighter-0.49.0.dist-info/WHEEL
synnax_freighter-0.49.0.dist-info/RECORD
