Metadata-Version: 2.4
Name: synnax-freighter
Version: 0.49.0
Summary: 
Author: Emiliano Bonilla
Author-email: ebonilla@synnaxlabs.com
Requires-Python: >=3.11,<4
Classifier: Programming Language :: Python :: 3
Classifier: Programming Language :: Python :: 3.11
Classifier: Programming Language :: Python :: 3.12
Classifier: Programming Language :: Python :: 3.13
Classifier: Programming Language :: Python :: 3.14
Requires-Dist: alamos (>=0.49.0,<0.50.0)
Requires-Dist: msgpack (>=1.1.2,<2.0.0)
Requires-Dist: pydantic (>=2.12.4,<3.0.0)
Requires-Dist: urllib3 (>=2.5.0,<3.0.0)
Requires-Dist: websockets (>=15.0.1,<16.0.0)
